{
	"data":
		[
			{
				"temperature":"20.9",
				"humidity":"29",
				"voltage":"2.966",
				"humidityCalibrated":"22",
				"batteryLevel":"87",
				"timestamp":"1645815611"
			},
			{
				"temperature":"20.89",
				"humidity":"29",
				"voltage":"2.966",
				"humidityCalibrated":"22",
				"batteryLevel":"87",
				"timestamp":"1645815617"
			},
			{
				"temperature":"20.87",
				"humidity":"29",
				"voltage":"2.962",
				"humidityCalibrated":"22",
				"batteryLevel":"86",
				"timestamp":"1645819207"
			},
			{
				"temperature":"20.85",
				"humidity":"29",
				"voltage":"2.962",
				"humidityCalibrated":"22",
				"batteryLevel":"86",
				"timestamp":"1645819214"
			},
			{
				"temperature":"20.69",
				"humidity":"29",
				"voltage":"2.961",
				"humidityCalibrated":"22",
				"batteryLevel":"86",
				"timestamp":"1645822809"
			},
			{
				"temperature":"20.7",
				"humidity":"29",
				"voltage":"2.961",
				"humidityCalibrated":"22",
				"batteryLevel":"86",
				"timestamp":"1645822816"
			},
			{
				"temperature":"20.18",
				"humidity":"29",
				"voltage":"2.959",
				"humidityCalibrated":"22",
				"batteryLevel":"86",
				"timestamp":"1645826405"
			},
			{
				"temperature":"20.22",
				"humidity":"29",
				"voltage":"2.959",
				"humidityCalibrated":"22",
				"batteryLevel":"86",
				"timestamp":"1645826412"
			},
			{
				"temperature":"19.87",
				"humidity":"29",
				"voltage":"2.96",
				"humidityCalibrated":"22",
				"batteryLevel":"86",
				"timestamp":"1645830008"
			},
			{
				"temperature":"19.82",
				"humidity":"29",
				"voltage":"2.96",
				"humidityCalibrated":"22",
				"batteryLevel":"86",
				"timestamp":"1645830014"
			},
			{
				"temperature":"19.55",
				"humidity":"29",
				"voltage":"2.954",
				"humidityCalibrated":"22",
				"batteryLevel":"85",
				"timestamp":"1645833612"
			},
			{
				"temperature":"19.55",
				"humidity":"29",
				"voltage":"2.954",
				"humidityCalibrated":"22",
				"batteryLevel":"85",
				"timestamp":"1645833618"
			},
			{
				"temperature":"19.29",
				"humidity":"29",
				"voltage":"2.95",
				"humidityCalibrated":"22",
				"batteryLevel":"85",
				"timestamp":"1645837208"
			},
			{
				"temperature":"19.3",
				"humidity":"29",
				"voltage":"2.95",
				"humidityCalibrated":"22",
				"batteryLevel":"85",
				"timestamp":"1645837214"
			},
			{
				"temperature":"19.11",
				"humidity":"29",
				"voltage":"2.951",
				"humidityCalibrated":"22",
				"batteryLevel":"85",
				"timestamp":"1645840811"
			},
			{
				"temperature":"19.11",
				"humidity":"29",
				"voltage":"2.951",
				"humidityCalibrated":"22",
				"batteryLevel":"85",
				"timestamp":"1645840819"
			},
			{
				"temperature":"18.92",
				"humidity":"29",
				"voltage":"2.945",
				"humidityCalibrated":"22",
				"batteryLevel":"84",
				"timestamp":"1645844405"
			},
			{
				"temperature":"18.94",
				"humidity":"29",
				"voltage":"2.945",
				"humidityCalibrated":"22",
				"batteryLevel":"84",
				"timestamp":"1645844412"
			},
			{
				"temperature":"18.76",
				"humidity":"29",
				"voltage":"2.943",
				"humidityCalibrated":"22",
				"batteryLevel":"84",
				"timestamp":"1645848009"
			},
			{
				"temperature":"18.74",
				"humidity":"29",
				"voltage":"2.943",
				"humidityCalibrated":"22",
				"batteryLevel":"84",
				"timestamp":"1645848016"
			},
			{
				"temperature":"19.18",
				"humidity":"29",
				"voltage":"2.946",
				"humidityCalibrated":"22",
				"batteryLevel":"85",
				"timestamp":"1645851609"
			},
			{
				"temperature":"19.22",
				"humidity":"29",
				"voltage":"2.946",
				"humidityCalibrated":"22",
				"batteryLevel":"85",
				"timestamp":"1645851618"
			},
			{
				"temperature":"19.76",
				"humidity":"29",
				"voltage":"2.948",
				"humidityCalibrated":"22",
				"batteryLevel":"85",
				"timestamp":"1645855210"
			},
			{
				"temperature":"19.76",
				"humidity":"29",
				"voltage":"2.948",
				"humidityCalibrated":"22",
				"batteryLevel":"85",
				"timestamp":"1645855216"
			},
			{
				"temperature":"20.14",
				"humidity":"29",
				"voltage":"2.958",
				"humidityCalibrated":"22",
				"batteryLevel":"86",
				"timestamp":"1645858805"
			},
			{
				"temperature":"20.17",
				"humidity":"29",
				"voltage":"2.958",
				"humidityCalibrated":"22",
				"batteryLevel":"86",
				"timestamp":"1645858814"
			},
			{
				"temperature":"20.62",
				"humidity":"29",
				"voltage":"2.954",
				"humidityCalibrated":"22",
				"batteryLevel":"85",
				"timestamp":"1645862409"
			},
			{
				"temperature":"20.61",
				"humidity":"29",
				"voltage":"2.954",
				"humidityCalibrated":"22",
				"batteryLevel":"85",
				"timestamp":"1645862416"
			},
			{
				"temperature":"20.75",
				"humidity":"29",
				"voltage":"2.961",
				"humidityCalibrated":"22",
				"batteryLevel":"86",
				"timestamp":"1645866007"
			},
			{
				"temperature":"20.78",
				"humidity":"29",
				"voltage":"2.961",
				"humidityCalibrated":"22",
				"batteryLevel":"86",
				"timestamp":"1645866014"
			},
			{
				"temperature":"20.86",
				"humidity":"29",
				"voltage":"2.957",
				"humidityCalibrated":"22",
				"batteryLevel":"86",
				"timestamp":"1645869612"
			},
			{
				"temperature":"20.85",
				"humidity":"29",
				"voltage":"2.957",
				"humidityCalibrated":"22",
				"batteryLevel":"86",
				"timestamp":"1645869619"
			},
			{
				"temperature":"20.87",
				"humidity":"29",
				"voltage":"2.961",
				"humidityCalibrated":"22",
				"batteryLevel":"86",
				"timestamp":"1645873205"
			},
			{
				"temperature":"20.89",
				"humidity":"29",
				"voltage":"2.961",
				"humidityCalibrated":"22",
				"batteryLevel":"86",
				"timestamp":"1645873212"
			},
			{
				"temperature":"20.94",
				"humidity":"29",
				"voltage":"2.958",
				"humidityCalibrated":"22",
				"batteryLevel":"86",
				"timestamp":"1645876811"
			},
			{
				"temperature":"20.96",
				"humidity":"29",
				"voltage":"2.958",
				"humidityCalibrated":"22",
				"batteryLevel":"86",
				"timestamp":"1645876819"
			},
			{
				"temperature":"20.87",
				"humidity":"29",
				"voltage":"2.957",
				"humidityCalibrated":"22",
				"batteryLevel":"86",
				"timestamp":"1645880412"
			},
			{
				"temperature":"20.82",
				"humidity":"29",
				"voltage":"2.957",
				"humidityCalibrated":"22",
				"batteryLevel":"86",
				"timestamp":"1645880420"
			},
			{
				"temperature":"20.84",
				"humidity":"29",
				"voltage":"2.957",
				"humidityCalibrated":"22",
				"batteryLevel":"86",
				"timestamp":"1645884010"
			},
			{
				"temperature":"20.86",
				"humidity":"29",
				"voltage":"2.957",
				"humidityCalibrated":"22",
				"batteryLevel":"86",
				"timestamp":"1645884016"
			},
			{
				"temperature":"20.89",
				"humidity":"30",
				"voltage":"2.958",
				"humidityCalibrated":"24",
				"batteryLevel":"86",
				"timestamp":"1645887606"
			},
			{
				"temperature":"20.9",
				"humidity":"30",
				"voltage":"2.958",
				"humidityCalibrated":"24",
				"batteryLevel":"86",
				"timestamp":"1645887614"
			},
			{
				"temperature":"20.95",
				"humidity":"30",
				"voltage":"2.958",
				"humidityCalibrated":"24",
				"batteryLevel":"86",
				"timestamp":"1645891209"
			},
			{
				"temperature":"20.99",
				"humidity":"30",
				"voltage":"2.958",
				"humidityCalibrated":"24",
				"batteryLevel":"86",
				"timestamp":"1645891218"
			},
			{
				"temperature":"21.06",
				"humidity":"30",
				"voltage":"2.958",
				"humidityCalibrated":"24",
				"batteryLevel":"86",
				"timestamp":"1645894807"
			},
			{
				"temperature":"21.02",
				"humidity":"30",
				"voltage":"2.958",
				"humidityCalibrated":"24",
				"batteryLevel":"86",
				"timestamp":"1645894814"
			},
			{
				"temperature":"21.11",
				"humidity":"30",
				"voltage":"2.959",
				"humidityCalibrated":"24",
				"batteryLevel":"86",
				"timestamp":"1645898410"
			},
			{
				"temperature":"21.1",
				"humidity":"30",
				"voltage":"2.959",
				"humidityCalibrated":"24",
				"batteryLevel":"86",
				"timestamp":"1645898416"
			},
			{
				"temperature":"21.14",
				"humidity":"30",
				"voltage":"2.958",
				"humidityCalibrated":"24",
				"batteryLevel":"86",
				"timestamp":"1645902009"
			},
			{
				"temperature":"21.14",
				"humidity":"30",
				"voltage":"2.958",
				"humidityCalibrated":"24",
				"batteryLevel":"86",
				"timestamp":"1645902015"
			},
			{
				"temperature":"21.13",
				"humidity":"30",
				"voltage":"2.963",
				"humidityCalibrated":"24",
				"batteryLevel":"86",
				"timestamp":"1645905607"
			},
			{
				"temperature":"21.12",
				"humidity":"30",
				"voltage":"2.963",
				"humidityCalibrated":"24",
				"batteryLevel":"86",
				"timestamp":"1645905615"
			},
			{
				"temperature":"21.08",
				"humidity":"30",
				"voltage":"2.958",
				"humidityCalibrated":"24",
				"batteryLevel":"86",
				"timestamp":"1645909206"
			},
			{
				"temperature":"21.03",
				"humidity":"30",
				"voltage":"2.958",
				"humidityCalibrated":"24",
				"batteryLevel":"86",
				"timestamp":"1645909213"
			},
			{
				"temperature":"20.46",
				"humidity":"31",
				"voltage":"2.955",
				"humidityCalibrated":"25",
				"batteryLevel":"85",
				"timestamp":"1645912806"
			},
			{
				"temperature":"20.46",
				"humidity":"31",
				"voltage":"2.955",
				"humidityCalibrated":"25",
				"batteryLevel":"85",
				"timestamp":"1645912813"
			},
			{
				"temperature":"20.0",
				"humidity":"31",
				"voltage":"2.951",
				"humidityCalibrated":"25",
				"batteryLevel":"85",
				"timestamp":"1645916406"
			},
			{
				"temperature":"20.0",
				"humidity":"31",
				"voltage":"2.951",
				"humidityCalibrated":"25",
				"batteryLevel":"85",
				"timestamp":"1645916413"
			},
			{
				"temperature":"19.62",
				"humidity":"32",
				"voltage":"2.95",
				"humidityCalibrated":"26",
				"batteryLevel":"85",
				"timestamp":"1645920010"
			},
			{
				"temperature":"19.62",
				"humidity":"32",
				"voltage":"2.95",
				"humidityCalibrated":"26",
				"batteryLevel":"85",
				"timestamp":"1645920017"
			},
			{
				"temperature":"19.33",
				"humidity":"32",
				"voltage":"2.951",
				"humidityCalibrated":"26",
				"batteryLevel":"85",
				"timestamp":"1645923605"
			},
			{
				"temperature":"19.35",
				"humidity":"32",
				"voltage":"2.951",
				"humidityCalibrated":"26",
				"batteryLevel":"85",
				"timestamp":"1645923613"
			},
			{
				"temperature":"19.13",
				"humidity":"32",
				"voltage":"2.943",
				"humidityCalibrated":"26",
				"batteryLevel":"84",
				"timestamp":"1645927210"
			},
			{
				"temperature":"19.14",
				"humidity":"32",
				"voltage":"2.943",
				"humidityCalibrated":"26",
				"batteryLevel":"84",
				"timestamp":"1645927216"
			},
			{
				"temperature":"19.0",
				"humidity":"32",
				"voltage":"2.942",
				"humidityCalibrated":"26",
				"batteryLevel":"84",
				"timestamp":"1645930805"
			},
			{
				"temperature":"19.04",
				"humidity":"32",
				"voltage":"2.942",
				"humidityCalibrated":"26",
				"batteryLevel":"84",
				"timestamp":"1645930813"
			},
			{
				"temperature":"18.88",
				"humidity":"32",
				"voltage":"2.94",
				"humidityCalibrated":"26",
				"batteryLevel":"84",
				"timestamp":"1645934404"
			},
			{
				"temperature":"18.88",
				"humidity":"32",
				"voltage":"2.94",
				"humidityCalibrated":"26",
				"batteryLevel":"84",
				"timestamp":"1645934410"
			},
			{
				"temperature":"18.71",
				"humidity":"32",
				"voltage":"2.94",
				"humidityCalibrated":"26",
				"batteryLevel":"84",
				"timestamp":"1645938011"
			},
			{
				"temperature":"18.72",
				"humidity":"32",
				"voltage":"2.94",
				"humidityCalibrated":"26",
				"batteryLevel":"84",
				"timestamp":"1645938018"
			},
			{
				"temperature":"19.34",
				"humidity":"31",
				"voltage":"2.943",
				"humidityCalibrated":"25",
				"batteryLevel":"84",
				"timestamp":"1645941608"
			},
			{
				"temperature":"19.34",
				"humidity":"31",
				"voltage":"2.943",
				"humidityCalibrated":"25",
				"batteryLevel":"84",
				"timestamp":"1645941614"
			},
			{
				"temperature":"19.96",
				"humidity":"31",
				"voltage":"2.945",
				"humidityCalibrated":"25",
				"batteryLevel":"84",
				"timestamp":"1645945208"
			},
			{
				"temperature":"19.92",
				"humidity":"31",
				"voltage":"2.945",
				"humidityCalibrated":"25",
				"batteryLevel":"84",
				"timestamp":"1645945214"
			},
			{
				"temperature":"20.48",
				"humidity":"30",
				"voltage":"2.948",
				"humidityCalibrated":"24",
				"batteryLevel":"85",
				"timestamp":"1645948811"
			},
			{
				"temperature":"20.47",
				"humidity":"30",
				"voltage":"2.948",
				"humidityCalibrated":"24",
				"batteryLevel":"85",
				"timestamp":"1645948817"
			},
			{
				"temperature":"20.8",
				"humidity":"30",
				"voltage":"2.957",
				"humidityCalibrated":"24",
				"batteryLevel":"86",
				"timestamp":"1645952411"
			},
			{
				"temperature":"20.8",
				"humidity":"30",
				"voltage":"2.957",
				"humidityCalibrated":"24",
				"batteryLevel":"86",
				"timestamp":"1645952417"
			},
			{
				"temperature":"21.07",
				"humidity":"30",
				"voltage":"2.959",
				"humidityCalibrated":"24",
				"batteryLevel":"86",
				"timestamp":"1645956011"
			},
			{
				"temperature":"21.09",
				"humidity":"30",
				"voltage":"2.959",
				"humidityCalibrated":"24",
				"batteryLevel":"86",
				"timestamp":"1645956017"
			},
			{
				"temperature":"21.1",
				"humidity":"29",
				"voltage":"2.953",
				"humidityCalibrated":"22",
				"batteryLevel":"85",
				"timestamp":"1645959614"
			},
			{
				"temperature":"21.13",
				"humidity":"29",
				"voltage":"2.953",
				"humidityCalibrated":"22",
				"batteryLevel":"85",
				"timestamp":"1645959620"
			},
			{
				"temperature":"21.16",
				"humidity":"29",
				"voltage":"2.959",
				"humidityCalibrated":"22",
				"batteryLevel":"86",
				"timestamp":"1645963206"
			},
			{
				"temperature":"21.16",
				"humidity":"29",
				"voltage":"2.959",
				"humidityCalibrated":"22",
				"batteryLevel":"86",
				"timestamp":"1645963213"
			},
			{
				"temperature":"21.15",
				"humidity":"29",
				"voltage":"2.954",
				"humidityCalibrated":"22",
				"batteryLevel":"85",
				"timestamp":"1645966811"
			},
			{
				"temperature":"21.16",
				"humidity":"29",
				"voltage":"2.954",
				"humidityCalibrated":"22",
				"batteryLevel":"85",
				"timestamp":"1645966818"
			},
			{
				"temperature":"21.12",
				"humidity":"29",
				"voltage":"2.955",
				"humidityCalibrated":"22",
				"batteryLevel":"85",
				"timestamp":"1645970406"
			},
			{
				"temperature":"21.14",
				"humidity":"29",
				"voltage":"2.955",
				"humidityCalibrated":"22",
				"batteryLevel":"85",
				"timestamp":"1645970413"
			},
			{
				"temperature":"20.93",
				"humidity":"29",
				"voltage":"2.955",
				"humidityCalibrated":"22",
				"batteryLevel":"85",
				"timestamp":"1645974009"
			},
			{
				"temperature":"20.95",
				"humidity":"29",
				"voltage":"2.955",
				"humidityCalibrated":"22",
				"batteryLevel":"85",
				"timestamp":"1645974016"
			},
			{
				"temperature":"20.89",
				"humidity":"29",
				"voltage":"2.959",
				"humidityCalibrated":"22",
				"batteryLevel":"86",
				"timestamp":"1645977606"
			},
			{
				"temperature":"20.88",
				"humidity":"29",
				"voltage":"2.959",
				"humidityCalibrated":"22",
				"batteryLevel":"86",
				"timestamp":"1645977613"
			},
			{
				"temperature":"20.91",
				"humidity":"29",
				"voltage":"2.954",
				"humidityCalibrated":"22",
				"batteryLevel":"85",
				"timestamp":"1645981211"
			},
			{
				"temperature":"20.92",
				"humidity":"29",
				"voltage":"2.954",
				"humidityCalibrated":"22",
				"batteryLevel":"85",
				"timestamp":"1645981217"
			},
			{
				"temperature":"20.92",
				"humidity":"29",
				"voltage":"2.952",
				"humidityCalibrated":"22",
				"batteryLevel":"85",
				"timestamp":"1645984813"
			},
			{
				"temperature":"20.88",
				"humidity":"29",
				"voltage":"2.952",
				"humidityCalibrated":"22",
				"batteryLevel":"85",
				"timestamp":"1645984819"
			},
			{
				"temperature":"20.87",
				"humidity":"29",
				"voltage":"2.952",
				"humidityCalibrated":"22",
				"batteryLevel":"85",
				"timestamp":"1645988406"
			},
			{
				"temperature":"20.88",
				"humidity":"29",
				"voltage":"2.952",
				"humidityCalibrated":"22",
				"batteryLevel":"85",
				"timestamp":"1645988413"
			},
			{
				"temperature":"20.82",
				"humidity":"29",
				"voltage":"2.953",
				"humidityCalibrated":"22",
				"batteryLevel":"85",
				"timestamp":"1645992006"
			},
			{
				"temperature":"20.8",
				"humidity":"29",
				"voltage":"2.953",
				"humidityCalibrated":"22",
				"batteryLevel":"85",
				"timestamp":"1645992012"
			},
			{
				"temperature":"20.69",
				"humidity":"29",
				"voltage":"2.958",
				"humidityCalibrated":"22",
				"batteryLevel":"86",
				"timestamp":"1645995612"
			},
			{
				"temperature":"20.68",
				"humidity":"29",
				"voltage":"2.958",
				"humidityCalibrated":"22",
				"batteryLevel":"86",
				"timestamp":"1645995618"
			},
			{
				"temperature":"20.13",
				"humidity":"30",
				"voltage":"2.95",
				"humidityCalibrated":"24",
				"batteryLevel":"85",
				"timestamp":"1645999211"
			},
			{
				"temperature":"20.14",
				"humidity":"30",
				"voltage":"2.95",
				"humidityCalibrated":"24",
				"batteryLevel":"85",
				"timestamp":"1645999219"
			},
			{
				"temperature":"19.66",
				"humidity":"30",
				"voltage":"2.952",
				"humidityCalibrated":"24",
				"batteryLevel":"85",
				"timestamp":"1646002806"
			},
			{
				"temperature":"19.66",
				"humidity":"30",
				"voltage":"2.952",
				"humidityCalibrated":"24",
				"batteryLevel":"85",
				"timestamp":"1646002813"
			},
			{
				"temperature":"19.39",
				"humidity":"30",
				"voltage":"2.945",
				"humidityCalibrated":"24",
				"batteryLevel":"84",
				"timestamp":"1646006406"
			},
			{
				"temperature":"19.37",
				"humidity":"30",
				"voltage":"2.945",
				"humidityCalibrated":"24",
				"batteryLevel":"84",
				"timestamp":"1646006414"
			},
			{
				"temperature":"19.17",
				"humidity":"30",
				"voltage":"2.943",
				"humidityCalibrated":"24",
				"batteryLevel":"84",
				"timestamp":"1646010010"
			},
			{
				"temperature":"19.18",
				"humidity":"30",
				"voltage":"2.943",
				"humidityCalibrated":"24",
				"batteryLevel":"84",
				"timestamp":"1646010016"
			},
			{
				"temperature":"19.04",
				"humidity":"31",
				"voltage":"2.938",
				"humidityCalibrated":"25",
				"batteryLevel":"84",
				"timestamp":"1646013612"
			},
			{
				"temperature":"19.05",
				"humidity":"31",
				"voltage":"2.938",
				"humidityCalibrated":"25",
				"batteryLevel":"84",
				"timestamp":"1646013618"
			},
			{
				"temperature":"18.82",
				"humidity":"31",
				"voltage":"2.938",
				"humidityCalibrated":"25",
				"batteryLevel":"84",
				"timestamp":"1646017205"
			},
			{
				"temperature":"18.84",
				"humidity":"31",
				"voltage":"2.938",
				"humidityCalibrated":"25",
				"batteryLevel":"84",
				"timestamp":"1646017212"
			},
			{
				"temperature":"18.63",
				"humidity":"31",
				"voltage":"2.938",
				"humidityCalibrated":"25",
				"batteryLevel":"84",
				"timestamp":"1646020810"
			},
			{
				"temperature":"18.63",
				"humidity":"31",
				"voltage":"2.938",
				"humidityCalibrated":"25",
				"batteryLevel":"84",
				"timestamp":"1646020817"
			},
			{
				"temperature":"19.17",
				"humidity":"31",
				"voltage":"2.938",
				"humidityCalibrated":"25",
				"batteryLevel":"84",
				"timestamp":"1646024406"
			},
			{
				"temperature":"19.17",
				"humidity":"31",
				"voltage":"2.938",
				"humidityCalibrated":"25",
				"batteryLevel":"84",
				"timestamp":"1646024413"
			},
			{
				"temperature":"19.7",
				"humidity":"30",
				"voltage":"2.939",
				"humidityCalibrated":"24",
				"batteryLevel":"84",
				"timestamp":"1646028006"
			},
			{
				"temperature":"19.71",
				"humidity":"30",
				"voltage":"2.939",
				"humidityCalibrated":"24",
				"batteryLevel":"84",
				"timestamp":"1646028012"
			},
			{
				"temperature":"20.11",
				"humidity":"30",
				"voltage":"2.944",
				"humidityCalibrated":"24",
				"batteryLevel":"84",
				"timestamp":"1646031606"
			},
			{
				"temperature":"20.12",
				"humidity":"30",
				"voltage":"2.944",
				"humidityCalibrated":"24",
				"batteryLevel":"84",
				"timestamp":"1646031613"
			},
			{
				"temperature":"20.23",
				"humidity":"29",
				"voltage":"2.944",
				"humidityCalibrated":"22",
				"batteryLevel":"84",
				"timestamp":"1646035206"
			},
			{
				"temperature":"20.25",
				"humidity":"29",
				"voltage":"2.944",
				"humidityCalibrated":"22",
				"batteryLevel":"84",
				"timestamp":"1646035214"
			},
			{
				"temperature":"20.39",
				"humidity":"29",
				"voltage":"2.946",
				"humidityCalibrated":"22",
				"batteryLevel":"85",
				"timestamp":"1646038807"
			},
			{
				"temperature":"20.35",
				"humidity":"29",
				"voltage":"2.946",
				"humidityCalibrated":"22",
				"batteryLevel":"85",
				"timestamp":"1646038814"
			},
			{
				"temperature":"20.48",
				"humidity":"29",
				"voltage":"2.95",
				"humidityCalibrated":"22",
				"batteryLevel":"85",
				"timestamp":"1646042405"
			},
			{
				"temperature":"20.5",
				"humidity":"29",
				"voltage":"2.95",
				"humidityCalibrated":"22",
				"batteryLevel":"85",
				"timestamp":"1646042414"
			},
			{
				"temperature":"20.55",
				"humidity":"29",
				"voltage":"2.947",
				"humidityCalibrated":"22",
				"batteryLevel":"85",
				"timestamp":"1646046006"
			},
			{
				"temperature":"20.59",
				"humidity":"29",
				"voltage":"2.947",
				"humidityCalibrated":"22",
				"batteryLevel":"85",
				"timestamp":"1646046013"
			},
			{
				"temperature":"20.64",
				"humidity":"29",
				"voltage":"2.952",
				"humidityCalibrated":"22",
				"batteryLevel":"85",
				"timestamp":"1646049610"
			},
			{
				"temperature":"20.63",
				"humidity":"29",
				"voltage":"2.952",
				"humidityCalibrated":"22",
				"batteryLevel":"85",
				"timestamp":"1646049616"
			},
			{
				"temperature":"20.7",
				"humidity":"29",
				"voltage":"2.95",
				"humidityCalibrated":"22",
				"batteryLevel":"85",
				"timestamp":"1646053212"
			},
			{
				"temperature":"20.7",
				"humidity":"29",
				"voltage":"2.95",
				"humidityCalibrated":"22",
				"batteryLevel":"85",
				"timestamp":"1646053218"
			},
			{
				"temperature":"20.92",
				"humidity":"29",
				"voltage":"2.951",
				"humidityCalibrated":"22",
				"batteryLevel":"85",
				"timestamp":"1646056808"
			},
			{
				"temperature":"20.9",
				"humidity":"29",
				"voltage":"2.951",
				"humidityCalibrated":"22",
				"batteryLevel":"85",
				"timestamp":"1646056815"
			},
			{
				"temperature":"20.89",
				"humidity":"29",
				"voltage":"2.951",
				"humidityCalibrated":"22",
				"batteryLevel":"85",
				"timestamp":"1646060407"
			},
			{
				"temperature":"20.86",
				"humidity":"29",
				"voltage":"2.951",
				"humidityCalibrated":"22",
				"batteryLevel":"85",
				"timestamp":"1646060413"
			},
			{
				"temperature":"20.82",
				"humidity":"29",
				"voltage":"2.951",
				"humidityCalibrated":"22",
				"batteryLevel":"85",
				"timestamp":"1646064009"
			},
			{
				"temperature":"20.82",
				"humidity":"29",
				"voltage":"2.951",
				"humidityCalibrated":"22",
				"batteryLevel":"85",
				"timestamp":"1646064016"
			},
			{
				"temperature":"20.69",
				"humidity":"29",
				"voltage":"2.951",
				"humidityCalibrated":"22",
				"batteryLevel":"85",
				"timestamp":"1646067610"
			},
			{
				"temperature":"20.68",
				"humidity":"29",
				"voltage":"2.951",
				"humidityCalibrated":"22",
				"batteryLevel":"85",
				"timestamp":"1646067616"
			},
			{
				"temperature":"20.64",
				"humidity":"29",
				"voltage":"2.951",
				"humidityCalibrated":"22",
				"batteryLevel":"85",
				"timestamp":"1646071205"
			},
			{
				"temperature":"20.64",
				"humidity":"29",
				"voltage":"2.951",
				"humidityCalibrated":"22",
				"batteryLevel":"85",
				"timestamp":"1646071213"
			},
			{
				"temperature":"20.64",
				"humidity":"29",
				"voltage":"2.954",
				"humidityCalibrated":"22",
				"batteryLevel":"85",
				"timestamp":"1646074808"
			},
			{
				"temperature":"20.64",
				"humidity":"29",
				"voltage":"2.954",
				"humidityCalibrated":"22",
				"batteryLevel":"85",
				"timestamp":"1646074815"
			},
			{
				"temperature":"20.65",
				"humidity":"29",
				"voltage":"2.948",
				"humidityCalibrated":"22",
				"batteryLevel":"85",
				"timestamp":"1646078410"
			},
			{
				"temperature":"20.68",
				"humidity":"29",
				"voltage":"2.948",
				"humidityCalibrated":"22",
				"batteryLevel":"85",
				"timestamp":"1646078418"
			},
			{
				"temperature":"20.55",
				"humidity":"29",
				"voltage":"2.957",
				"humidityCalibrated":"22",
				"batteryLevel":"86",
				"timestamp":"1646082014"
			},
			{
				"temperature":"20.57",
				"humidity":"29",
				"voltage":"2.957",
				"humidityCalibrated":"22",
				"batteryLevel":"86",
				"timestamp":"1646082020"
			},
			{
				"temperature":"19.93",
				"humidity":"30",
				"voltage":"2.945",
				"humidityCalibrated":"24",
				"batteryLevel":"84",
				"timestamp":"1646085607"
			},
			{
				"temperature":"19.92",
				"humidity":"30",
				"voltage":"2.945",
				"humidityCalibrated":"24",
				"batteryLevel":"84",
				"timestamp":"1646085614"
			},
			{
				"temperature":"19.46",
				"humidity":"30",
				"voltage":"2.947",
				"humidityCalibrated":"24",
				"batteryLevel":"85",
				"timestamp":"1646089205"
			},
			{
				"temperature":"19.43",
				"humidity":"30",
				"voltage":"2.947",
				"humidityCalibrated":"24",
				"batteryLevel":"85",
				"timestamp":"1646089212"
			},
			{
				"temperature":"19.13",
				"humidity":"30",
				"voltage":"2.94",
				"humidityCalibrated":"24",
				"batteryLevel":"84",
				"timestamp":"1646092810"
			},
			{
				"temperature":"19.12",
				"humidity":"30",
				"voltage":"2.94",
				"humidityCalibrated":"24",
				"batteryLevel":"84",
				"timestamp":"1646092817"
			},
			{
				"temperature":"18.93",
				"humidity":"30",
				"voltage":"2.939",
				"humidityCalibrated":"24",
				"batteryLevel":"84",
				"timestamp":"1646096411"
			},
			{
				"temperature":"18.96",
				"humidity":"30",
				"voltage":"2.939",
				"humidityCalibrated":"24",
				"batteryLevel":"84",
				"timestamp":"1646096417"
			},
			{
				"temperature":"18.74",
				"humidity":"30",
				"voltage":"2.936",
				"humidityCalibrated":"24",
				"batteryLevel":"84",
				"timestamp":"1646100009"
			},
			{
				"temperature":"18.69",
				"humidity":"30",
				"voltage":"2.936",
				"humidityCalibrated":"24",
				"batteryLevel":"84",
				"timestamp":"1646100015"
			},
			{
				"temperature":"18.48",
				"humidity":"30",
				"voltage":"2.936",
				"humidityCalibrated":"24",
				"batteryLevel":"84",
				"timestamp":"1646103607"
			},
			{
				"temperature":"18.51",
				"humidity":"31",
				"voltage":"2.936",
				"humidityCalibrated":"25",
				"batteryLevel":"84",
				"timestamp":"1646103615"
			},
			{
				"temperature":"18.31",
				"humidity":"31",
				"voltage":"2.935",
				"humidityCalibrated":"25",
				"batteryLevel":"83",
				"timestamp":"1646107218"
			},
			{
				"temperature":"18.3",
				"humidity":"31",
				"voltage":"2.874",
				"humidityCalibrated":"25",
				"batteryLevel":"77",
				"timestamp":"1646107224"
			},
			{
				"temperature":"18.91",
				"humidity":"30",
				"voltage":"2.936",
				"humidityCalibrated":"24",
				"batteryLevel":"84",
				"timestamp":"1646110808"
			},
			{
				"temperature":"18.91",
				"humidity":"30",
				"voltage":"2.936",
				"humidityCalibrated":"24",
				"batteryLevel":"84",
				"timestamp":"1646110815"
			},
			{
				"temperature":"19.62",
				"humidity":"30",
				"voltage":"2.938",
				"humidityCalibrated":"24",
				"batteryLevel":"84",
				"timestamp":"1646114408"
			},
			{
				"temperature":"19.61",
				"humidity":"30",
				"voltage":"2.938",
				"humidityCalibrated":"24",
				"batteryLevel":"84",
				"timestamp":"1646114415"
			},
			{
				"temperature":"19.99",
				"humidity":"29",
				"voltage":"2.94",
				"humidityCalibrated":"22",
				"batteryLevel":"84",
				"timestamp":"1646118005"
			},
			{
				"temperature":"20.0",
				"humidity":"29",
				"voltage":"2.94",
				"humidityCalibrated":"22",
				"batteryLevel":"84",
				"timestamp":"1646118012"
			},
			{
				"temperature":"20.14",
				"humidity":"29",
				"voltage":"2.946",
				"humidityCalibrated":"22",
				"batteryLevel":"85",
				"timestamp":"1646121611"
			},
			{
				"temperature":"20.15",
				"humidity":"29",
				"voltage":"2.907",
				"humidityCalibrated":"22",
				"batteryLevel":"81",
				"timestamp":"1646121617"
			},
			{
				"temperature":"20.48",
				"humidity":"29",
				"voltage":"2.904",
				"humidityCalibrated":"22",
				"batteryLevel":"80",
				"timestamp":"1646125210"
			},
			{
				"temperature":"20.44",
				"humidity":"29",
				"voltage":"2.904",
				"humidityCalibrated":"22",
				"batteryLevel":"80",
				"timestamp":"1646125219"
			},
			{
				"temperature":"20.69",
				"humidity":"29",
				"voltage":"2.916",
				"humidityCalibrated":"22",
				"batteryLevel":"82",
				"timestamp":"1646128812"
			},
			{
				"temperature":"20.72",
				"humidity":"29",
				"voltage":"2.916",
				"humidityCalibrated":"22",
				"batteryLevel":"82",
				"timestamp":"1646128818"
			},
			{
				"temperature":"20.7",
				"humidity":"29",
				"voltage":"2.954",
				"humidityCalibrated":"22",
				"batteryLevel":"85",
				"timestamp":"1646132407"
			},
			{
				"temperature":"20.69",
				"humidity":"29",
				"voltage":"2.954",
				"humidityCalibrated":"22",
				"batteryLevel":"85",
				"timestamp":"1646132415"
			},
			{
				"temperature":"20.68",
				"humidity":"29",
				"voltage":"2.948",
				"humidityCalibrated":"22",
				"batteryLevel":"85",
				"timestamp":"1646136009"
			},
			{
				"temperature":"20.67",
				"humidity":"29",
				"voltage":"2.948",
				"humidityCalibrated":"22",
				"batteryLevel":"85",
				"timestamp":"1646136015"
			},
			{
				"temperature":"20.94",
				"humidity":"29",
				"voltage":"2.951",
				"humidityCalibrated":"22",
				"batteryLevel":"85",
				"timestamp":"1646139606"
			},
			{
				"temperature":"20.92",
				"humidity":"29",
				"voltage":"2.951",
				"humidityCalibrated":"22",
				"batteryLevel":"85",
				"timestamp":"1646139615"
			},
			{
				"temperature":"20.9",
				"humidity":"29",
				"voltage":"2.95",
				"humidityCalibrated":"22",
				"batteryLevel":"85",
				"timestamp":"1646143214"
			},
			{
				"temperature":"20.87",
				"humidity":"29",
				"voltage":"2.95",
				"humidityCalibrated":"22",
				"batteryLevel":"85",
				"timestamp":"1646143220"
			},
			{
				"temperature":"20.75",
				"humidity":"29",
				"voltage":"2.954",
				"humidityCalibrated":"22",
				"batteryLevel":"85",
				"timestamp":"1646146813"
			},
			{
				"temperature":"20.74",
				"humidity":"29",
				"voltage":"2.954",
				"humidityCalibrated":"22",
				"batteryLevel":"85",
				"timestamp":"1646146820"
			},
			{
				"temperature":"20.68",
				"humidity":"29",
				"voltage":"2.948",
				"humidityCalibrated":"22",
				"batteryLevel":"85",
				"timestamp":"1646150414"
			},
			{
				"temperature":"20.66",
				"humidity":"29",
				"voltage":"2.948",
				"humidityCalibrated":"22",
				"batteryLevel":"85",
				"timestamp":"1646150423"
			},
			{
				"temperature":"20.61",
				"humidity":"29",
				"voltage":"2.947",
				"humidityCalibrated":"22",
				"batteryLevel":"85",
				"timestamp":"1646154009"
			},
			{
				"temperature":"20.61",
				"humidity":"29",
				"voltage":"2.947",
				"humidityCalibrated":"22",
				"batteryLevel":"85",
				"timestamp":"1646154015"
			},
			{
				"temperature":"20.59",
				"humidity":"29",
				"voltage":"2.952",
				"humidityCalibrated":"22",
				"batteryLevel":"85",
				"timestamp":"1646157613"
			},
			{
				"temperature":"20.6",
				"humidity":"29",
				"voltage":"2.952",
				"humidityCalibrated":"22",
				"batteryLevel":"85",
				"timestamp":"1646157621"
			},
			{
				"temperature":"20.61",
				"humidity":"29",
				"voltage":"2.947",
				"humidityCalibrated":"22",
				"batteryLevel":"85",
				"timestamp":"1646161217"
			},
			{
				"temperature":"20.59",
				"humidity":"29",
				"voltage":"2.947",
				"humidityCalibrated":"22",
				"batteryLevel":"85",
				"timestamp":"1646161223"
			},
			{
				"temperature":"20.61",
				"humidity":"29",
				"voltage":"2.95",
				"humidityCalibrated":"22",
				"batteryLevel":"85",
				"timestamp":"1646164813"
			},
			{
				"temperature":"20.61",
				"humidity":"29",
				"voltage":"2.95",
				"humidityCalibrated":"22",
				"batteryLevel":"85",
				"timestamp":"1646164819"
			},
			{
				"temperature":"20.41",
				"humidity":"29",
				"voltage":"2.945",
				"humidityCalibrated":"22",
				"batteryLevel":"84",
				"timestamp":"1646168411"
			},
			{
				"temperature":"20.44",
				"humidity":"29",
				"voltage":"2.945",
				"humidityCalibrated":"22",
				"batteryLevel":"84",
				"timestamp":"1646168419"
			},
			{
				"temperature":"19.79",
				"humidity":"29",
				"voltage":"2.944",
				"humidityCalibrated":"22",
				"batteryLevel":"84",
				"timestamp":"1646172010"
			},
			{
				"temperature":"19.83",
				"humidity":"29",
				"voltage":"2.944",
				"humidityCalibrated":"22",
				"batteryLevel":"84",
				"timestamp":"1646172016"
			},
			{
				"temperature":"19.36",
				"humidity":"29",
				"voltage":"2.946",
				"humidityCalibrated":"22",
				"batteryLevel":"85",
				"timestamp":"1646175610"
			},
			{
				"temperature":"19.33",
				"humidity":"29",
				"voltage":"2.946",
				"humidityCalibrated":"22",
				"batteryLevel":"85",
				"timestamp":"1646175617"
			},
			{
				"temperature":"18.98",
				"humidity":"29",
				"voltage":"2.938",
				"humidityCalibrated":"22",
				"batteryLevel":"84",
				"timestamp":"1646179212"
			},
			{
				"temperature":"19.02",
				"humidity":"29",
				"voltage":"2.938",
				"humidityCalibrated":"22",
				"batteryLevel":"84",
				"timestamp":"1646179218"
			},
			{
				"temperature":"18.68",
				"humidity":"29",
				"voltage":"2.936",
				"humidityCalibrated":"22",
				"batteryLevel":"84",
				"timestamp":"1646182809"
			},
			{
				"temperature":"18.69",
				"humidity":"29",
				"voltage":"2.936",
				"humidityCalibrated":"22",
				"batteryLevel":"84",
				"timestamp":"1646182815"
			},
			{
				"temperature":"18.49",
				"humidity":"29",
				"voltage":"2.936",
				"humidityCalibrated":"22",
				"batteryLevel":"84",
				"timestamp":"1646186409"
			},
			{
				"temperature":"18.49",
				"humidity":"29",
				"voltage":"2.936",
				"humidityCalibrated":"22",
				"batteryLevel":"84",
				"timestamp":"1646186415"
			},
			{
				"temperature":"18.25",
				"humidity":"29",
				"voltage":"2.936",
				"humidityCalibrated":"22",
				"batteryLevel":"84",
				"timestamp":"1646190009"
			},
			{
				"temperature":"18.24",
				"humidity":"29",
				"voltage":"2.936",
				"humidityCalibrated":"22",
				"batteryLevel":"84",
				"timestamp":"1646190016"
			},
			{
				"temperature":"18.1",
				"humidity":"29",
				"voltage":"2.937",
				"humidityCalibrated":"22",
				"batteryLevel":"84",
				"timestamp":"1646193606"
			},
			{
				"temperature":"18.1",
				"humidity":"29",
				"voltage":"2.937",
				"humidityCalibrated":"22",
				"batteryLevel":"84",
				"timestamp":"1646193613"
			},
			{
				"temperature":"18.6",
				"humidity":"28",
				"voltage":"2.936",
				"humidityCalibrated":"21",
				"batteryLevel":"84",
				"timestamp":"1646197209"
			},
			{
				"temperature":"18.62",
				"humidity":"28",
				"voltage":"2.936",
				"humidityCalibrated":"21",
				"batteryLevel":"84",
				"timestamp":"1646197215"
			},
			{
				"temperature":"19.26",
				"humidity":"28",
				"voltage":"2.937",
				"humidityCalibrated":"21",
				"batteryLevel":"84",
				"timestamp":"1646200810"
			},
			{
				"temperature":"19.26",
				"humidity":"28",
				"voltage":"2.937",
				"humidityCalibrated":"21",
				"batteryLevel":"84",
				"timestamp":"1646200816"
			},
			{
				"temperature":"19.75",
				"humidity":"27",
				"voltage":"2.938",
				"humidityCalibrated":"20",
				"batteryLevel":"84",
				"timestamp":"1646204411"
			},
			{
				"temperature":"19.73",
				"humidity":"27",
				"voltage":"2.938",
				"humidityCalibrated":"20",
				"batteryLevel":"84",
				"timestamp":"1646204417"
			},
			{
				"temperature":"20.11",
				"humidity":"27",
				"voltage":"2.942",
				"humidityCalibrated":"20",
				"batteryLevel":"84",
				"timestamp":"1646208009"
			},
			{
				"temperature":"20.11",
				"humidity":"27",
				"voltage":"2.942",
				"humidityCalibrated":"20",
				"batteryLevel":"84",
				"timestamp":"1646208015"
			},
			{
				"temperature":"20.3",
				"humidity":"27",
				"voltage":"2.945",
				"humidityCalibrated":"20",
				"batteryLevel":"84",
				"timestamp":"1646211610"
			},
			{
				"temperature":"20.34",
				"humidity":"27",
				"voltage":"2.945",
				"humidityCalibrated":"20",
				"batteryLevel":"84",
				"timestamp":"1646211619"
			},
			{
				"temperature":"20.39",
				"humidity":"27",
				"voltage":"2.952",
				"humidityCalibrated":"20",
				"batteryLevel":"85",
				"timestamp":"1646215208"
			},
			{
				"temperature":"20.41",
				"humidity":"27",
				"voltage":"2.952",
				"humidityCalibrated":"20",
				"batteryLevel":"85",
				"timestamp":"1646215215"
			}
		]
}
